zone_detector/__init__.py
zone_detector/cli.py
zone_detector/core/__init__.py
zone_detector/core/frame_renderer.py
zone_detector/core/person_tracker.py
zone_detector/core/rtmp_streamer.py
zone_detector/core/yolo_model.py
zone_detector/core/zone_manager.py
zone_detector/detection_streamer.py
zone_detection-0.1.1.dist-info/entry_points.txt
zone_detection-0.1.1.dist-info/METADATA
zone_detection-0.1.1.dist-info/WHEEL
zone_detection-0.1.1.dist-info/RECORD
